DolphinLanguageSDK/__init__.py
dolphin/__init__.py
dolphin/cli/__init__.py
dolphin/cli/main.py
dolphin/cli/args/__init__.py
dolphin/cli/args/parser.py
dolphin/cli/builtin_agents/__init__.py
dolphin/cli/commands/__init__.py
dolphin/cli/interrupt/__init__.py
dolphin/cli/interrupt/handler.py
dolphin/cli/interrupt/keyboard.py
dolphin/cli/multimodal/__init__.py
dolphin/cli/multimodal/clipboard.py
dolphin/cli/multimodal/handler.py
dolphin/cli/multimodal/image_processor.py
dolphin/cli/multimodal/input_parser.py
dolphin/cli/runner/__init__.py
dolphin/cli/runner/runner.py
dolphin/cli/ui/__init__.py
dolphin/cli/ui/console.py
dolphin/cli/ui/input.py
dolphin/cli/ui/layout.py
dolphin/cli/ui/stream_renderer.py
dolphin/cli/utils/__init__.py
dolphin/cli/utils/helpers.py
dolphin/cli/utils/version.py
dolphin/core/__init__.py
dolphin/core/interfaces.py
dolphin/core/task_registry.py
dolphin/core/agent/__init__.py
dolphin/core/agent/agent_state.py
dolphin/core/agent/base_agent.py
dolphin/core/code_block/__init__.py
dolphin/core/code_block/agent_init_block.py
dolphin/core/code_block/assign_block.py
dolphin/core/code_block/basic_code_block.py
dolphin/core/code_block/explore_block.py
dolphin/core/code_block/explore_block_v2.py
dolphin/core/code_block/explore_strategy.py
dolphin/core/code_block/judge_block.py
dolphin/core/code_block/prompt_block.py
dolphin/core/code_block/skill_call_deduplicator.py
dolphin/core/code_block/tool_block.py
dolphin/core/common/__init__.py
dolphin/core/common/constants.py
dolphin/core/common/enums.py
dolphin/core/common/exceptions.py
dolphin/core/common/multimodal.py
dolphin/core/common/object_type.py
dolphin/core/common/output_format.py
dolphin/core/common/types.py
dolphin/core/config/__init__.py
dolphin/core/config/global_config.py
dolphin/core/config/ontology_config.py
dolphin/core/context/__init__.py
dolphin/core/context/context.py
dolphin/core/context/context_manager.py
dolphin/core/context/cow_context.py
dolphin/core/context/var_output.py
kweaver_dolphin-0.2.1.dist-info/licenses/LICENSE.txt
kweaver_dolphin-0.2.1.dist-info/METADATA
kweaver_dolphin-0.2.1.dist-info/WHEEL
kweaver_dolphin-0.2.1.dist-info/entry_points.txt
kweaver_dolphin-0.2.1.dist-info/top_level.txt
kweaver_dolphin-0.2.1.dist-info/RECORD
