Metadata-Version: 2.4
Name: kweaver-dolphin
Version: 0.2.1
Summary: Dolphin Language - An intelligent agent framework
Author-email: AnyData <contact@anydata.com>
License: Apache 2.0
Classifier: Development Status :: 4 - Beta
Classifier: Intended Audience :: Developers
Classifier: License :: OSI Approved :: Apache Software License
Classifier: Programming Language :: Python :: 3
Classifier: Programming Language :: Python :: 3.10
Classifier: Programming Language :: Python :: 3.11
Classifier: Programming Language :: Python :: 3.12
Requires-Python: >=3.10
License-File: LICENSE.txt
Requires-Dist: pydantic<3.0.0,>=2.0.0
Requires-Dist: PyYAML<7.0.0,>=6.0.1
Requires-Dist: openai<2.0.0,>=1.0.0
Requires-Dist: tiktoken<1.0.0,>=0.4.0
Requires-Dist: aiohttp<4.0.0,>=3.9.0
Requires-Dist: aiofiles>=23.0.0
Requires-Dist: requests>=2.31.0
Requires-Dist: docstring-parser>=0.15
Requires-Dist: jsonschema>=4.17.0
Requires-Dist: rich<15.0.0,>=14.0.0
Provides-Extra: lib
Requires-Dist: mcp<2.0.0,>=1.0.0; extra == "lib"
Requires-Dist: sqlalchemy<3.0.0,>=2.0.0; extra == "lib"
Requires-Dist: oracledb<3.0.0,>=2.2.0; extra == "lib"
Requires-Dist: rank-bm25<1.0.0,>=0.2.0; extra == "lib"
Requires-Dist: paramiko>=3.5.0; extra == "lib"
Requires-Dist: cryptography>=43.0.0; extra == "lib"
Requires-Dist: pandas; extra == "lib"
Provides-Extra: cli
Requires-Dist: rich<15.0.0,>=14.0.0; extra == "cli"
Requires-Dist: prompt_toolkit<4.0.0,>=3.0.0; extra == "cli"
Provides-Extra: full
Requires-Dist: kweaver-dolphin[lib]; extra == "full"
Requires-Dist: kweaver-dolphin[cli]; extra == "full"
Provides-Extra: dev
Requires-Dist: kweaver-dolphin[full]; extra == "dev"
Requires-Dist: pytest>=7.0.0; extra == "dev"
Requires-Dist: pytest-asyncio>=0.21.0; extra == "dev"
Requires-Dist: pytest-cov>=4.0.0; extra == "dev"
Requires-Dist: ruff>=0.1.0; extra == "dev"
Requires-Dist: black>=23.0.0; extra == "dev"
Requires-Dist: mypy>=1.0.0; extra == "dev"
Dynamic: license-file
